[{
  "_id": {
    "$oid": "651d774e15da850d13860a78"
  },
  "project": "techno",
  "name": "old",
  "email": "rohangautam567@gmail.com",
  "url": "https://www.nishikaindia.com",
  "message": "eihfoeas",
  "__v": 0
},
{
  "_id": {
    "$oid": "651d785720e0008e204d419c"
  },
  "project": "techno",
  "name": "old",
  "email": "rohangautam567@gmail.com",
  "url": "https://www.nishikaindia.com",
  "message": "jfj",
  "__v": 0
},
{
  "_id": {
    "$oid": "651e405badedeaa21fbca3f9"
  },
  "project": "Technology Twist",
  "name": "Ankush Saraswat",
  "email": "ankush@gmail.com",
  "url": "https://technotwist.in",
  "message": "hello ",
  "__v": 0
},
{
  "_id": {
    "$oid": "651e80f3fbe1cd4dfffb5076"
  },
  "project": "Technology Twist",
  "name": "Ankush Saraswat",
  "email": "ankush@gmail.com",
  "url": "https://technotwist.in",
  "message": "rohan send\r\n",
  "__v": 0
},
{
  "_id": {
    "$oid": "651fc6266bd1ca3816985028"
  },
  "project": "tech",
  "name": "pos",
  "email": "admin@gmail.com",
  "url": "https://fksjd.com",
  "message": "welkefh",
  "__v": 0
},
{
  "_id": {
    "$oid": "651fe6cb82626a6f33e8a59e"
  },
  "project": "tech",
  "name": "pos",
  "email": "admin@gmail.com",
  "url": "https://fksjd.com",
  "message": "welkefh",
  "__v": 0
},
{
  "_id": {
    "$oid": "651fe6ce82626a6f33e8a59f"
  },
  "project": "techno",
  "name": "old",
  "email": "rohangautam567@gmail.com",
  "url": "https://www.nishikaindia.com",
  "message": "eihfoeas",
  "__v": 0
},
{
  "_id": {
    "$oid": "651fe6d182626a6f33e8a5a0"
  },
  "project": "techno",
  "name": "old",
  "email": "rohangautam567@gmail.com",
  "url": "https://www.nishikaindia.com",
  "message": "eihfoeas",
  "__v": 0
},
{
  "_id": {
    "$oid": "651fe6d482626a6f33e8a5a1"
  },
  "project": "tech",
  "name": "pos",
  "email": "admin@gmail.com",
  "url": "https://fksjd.com",
  "message": "welkefh",
  "__v": 0
},
{
  "_id": {
    "$oid": "651fe6f282626a6f33e8a5a2"
  },
  "project": "tech",
  "name": "pos",
  "email": "admin@gmail.com",
  "url": "https://fksjd.com",
  "message": "welkefh",
  "__v": 0
},
{
  "_id": {
    "$oid": "65278d51d36a05ca435a1257"
  },
  "project": "tech",
  "name": "pos",
  "email": "admin@gmail.com",
  "url": "https://fksjd.com",
  "message": "welkefh",
  "__v": 0
},
{
  "_id": {
    "$oid": "652cf761c1bb4c11c9388825"
  },
  "project": "techno",
  "name": "old",
  "email": "goutamrohanraj@gmail.com",
  "url": "https://www.nishikaindianishikaindianishikaindianishikaindianishikaindianishikaindianishikaindia.com",
  "message": "af",
  "__v": 0
}]